{
  "checked_utc": "2026-06-21T02:06:25+00:00",
  "domains": [
    {
      "domain": "totalsportek.tech",
      "lands_on": "self",
      "status": "Live (200)",
      "final_url": "https://totalsportek.tech/",
      "last_checked": "2026-06-21",
      "history": [
        {
          "date": "2026-06-21",
          "change": "Baseline: lands on self"
        }
      ]
    },
    {
      "domain": "totalsportek.bio",
      "lands_on": "self",
      "status": "Live (200)",
      "final_url": "https://totalsportek.bio/",
      "last_checked": "2026-06-21",
      "history": [
        {
          "date": "2026-06-21",
          "change": "Baseline: lands on self"
        }
      ]
    },
    {
      "domain": "totalsportek.cfd",
      "lands_on": "totalsportek.bio",
      "status": "Redirect (301) -> totalsportek.bio",
      "final_url": "https://totalsportek.bio/",
      "last_checked": "2026-06-21",
      "history": [
        {
          "date": "2026-06-21",
          "change": "Baseline: lands on totalsportek.bio"
        }
      ]
    },
    {
      "domain": "totalsportek.host",
      "lands_on": "dead",
      "status": "Dead",
      "final_url": null,
      "last_checked": "2026-06-21",
      "history": [
        {
          "date": "2026-06-21",
          "change": "Baseline: lands on dead"
        }
      ]
    },
    {
      "domain": "totalsportek.it",
      "lands_on": "totalsportek.bio",
      "status": "Redirect (301) -> totalsportek.bio",
      "final_url": "https://totalsportek.bio/",
      "last_checked": "2026-06-21",
      "history": [
        {
          "date": "2026-06-21",
          "change": "Baseline: lands on totalsportek.bio"
        }
      ]
    },
    {
      "domain": "totalsportekz.com",
      "lands_on": "self",
      "status": "Live (200)",
      "final_url": "https://totalsportekz.com/",
      "last_checked": "2026-06-21",
      "history": [
        {
          "date": "2026-06-21",
          "change": "Baseline: lands on self"
        }
      ]
    },
    {
      "domain": "totalsportekz.app",
      "lands_on": "self",
      "status": "Live (200)",
      "final_url": "https://totalsportekz.app/",
      "last_checked": "2026-06-21",
      "history": [
        {
          "date": "2026-06-21",
          "change": "Baseline: lands on self"
        }
      ]
    },
    {
      "domain": "totalsportek.gd",
      "lands_on": "totalsportekz.app",
      "status": "Redirect (301) -> totalsportekz.app",
      "final_url": "https://totalsportekz.app/",
      "last_checked": "2026-06-21",
      "history": [
        {
          "date": "2026-06-21",
          "change": "Baseline: lands on totalsportekz.app"
        }
      ]
    },
    {
      "domain": "totalsportek.li",
      "lands_on": "dead",
      "status": "Dead",
      "final_url": null,
      "last_checked": "2026-06-21",
      "history": [
        {
          "date": "2026-06-21",
          "change": "Baseline: lands on dead"
        }
      ]
    },
    {
      "domain": "totalsportek.ch",
      "lands_on": "dead",
      "status": "Dead",
      "final_url": null,
      "last_checked": "2026-06-21",
      "history": [
        {
          "date": "2026-06-21",
          "change": "Baseline: lands on dead"
        }
      ]
    },
    {
      "domain": "totalsportek.cv",
      "lands_on": "self",
      "status": "Live (200)",
      "final_url": "https://totalsportek.cv/",
      "last_checked": "2026-06-21",
      "history": [
        {
          "date": "2026-06-21",
          "change": "Baseline: lands on self"
        }
      ]
    },
    {
      "domain": "footybite.tech",
      "lands_on": "self",
      "status": "Live (200)",
      "final_url": "https://footybite.tech/",
      "last_checked": "2026-06-21",
      "history": [
        {
          "date": "2026-06-21",
          "change": "Baseline: lands on self"
        }
      ]
    },
    {
      "domain": "footybitez.app",
      "lands_on": "self",
      "status": "Live (200)",
      "final_url": "https://www.footybitez.app/",
      "last_checked": "2026-06-21",
      "history": [
        {
          "date": "2026-06-21",
          "change": "Baseline: lands on self"
        }
      ]
    },
    {
      "domain": "footybite.app",
      "lands_on": "self",
      "status": "Live (200)",
      "final_url": "https://footybite.app/",
      "last_checked": "2026-06-21",
      "history": [
        {
          "date": "2026-06-21",
          "change": "Baseline: lands on self"
        }
      ]
    },
    {
      "domain": "footybite.to",
      "lands_on": "footybitez.app",
      "status": "Redirect (301) -> footybitez.app",
      "final_url": "https://www.footybitez.app/",
      "last_checked": "2026-06-21",
      "history": [
        {
          "date": "2026-06-21",
          "change": "Baseline: lands on footybitez.app"
        }
      ]
    },
    {
      "domain": "freesportshd.sbs",
      "lands_on": "self",
      "status": "Live (200)",
      "final_url": "https://www.freesportshd.sbs/",
      "last_checked": "2026-06-21",
      "history": [
        {
          "date": "2026-06-21",
          "change": "Baseline: lands on self"
        }
      ]
    }
  ]
}